[
    { "Name": "Joakim", "imgurl": "https://example.com/images/joakim.jpg" },
    { "Name": "Joachim", "imgurl": "https://ca.slack-edge.com/T0F68FZ3R-U085MMEMJG6-ef99311c4bc9-512" },
    { "Name": "George", "imgurl": "https://example.com/images/george.jpg" },
    { "Name": "Baptiste", "imgurl": "https://ca.slack-edge.com/T0F68FZ3R-U06PLFTAAMD-13b7abeba1db-512" },
    { "Name": "Levi", "imgurl": "https://example.com/images/levi.jpg" },
    { "Name": "Kristoffer", "imgurl": "https://ca.slack-edge.com/T0F68FZ3R-U7NS67DPU-e2569c503582-72" },
    { "Name": "Pavlo", "imgurl": "https://example.com/images/pavlo.jpg" },
    { "Name": "Sverre", "imgurl": "https://example.com/images/sverre.jpg" }
  ]
  